traceflow/__init__.py
traceflow/__main__.py
traceflow/dev-requirements.txt
traceflow/parser.py
traceflow/pdf_generator.py
traceflow/test.json
traceflow/tests_runner.py
traceflow/utils.py
traceflow/version.py
traceflow/__pycache__/__init__.cpython-311.pyc
traceflow/__pycache__/__init__.cpython-39.pyc
traceflow/__pycache__/__main__.cpython-311.pyc
traceflow/__pycache__/__main__.cpython-39.pyc
traceflow/__pycache__/parser.cpython-311.pyc
traceflow/__pycache__/parser.cpython-39.pyc
traceflow/__pycache__/pdf_generator.cpython-311.pyc
traceflow/__pycache__/pdf_generator.cpython-39.pyc
traceflow/__pycache__/version.cpython-311.pyc
traceflow/__pycache__/version.cpython-39.pyc
traceflow/res/__init__.py
traceflow/res/report-header.tex
traceflow/res/traceflow-logo.png
traceflow/res/voxelflow-logo.png
traceflow/res/__pycache__/__init__.cpython-311.pyc
traceflow/res/__pycache__/__init__.cpython-39.pyc
traceflow_rtm-0.0.25.dist-info/METADATA
traceflow_rtm-0.0.25.dist-info/WHEEL
traceflow_rtm-0.0.25.dist-info/entry_points.txt
traceflow_rtm-0.0.25.dist-info/top_level.txt
traceflow_rtm-0.0.25.dist-info/RECORD
