Metadata-Version: 2.4
Name: traceflow-rtm
Version: 0.0.25
Summary: A Python library for managing software development documentation and testing that automates the generation of PDFs, validation packs, and traceability matrices.
Author: Bioxydyn Ltd
License-Expression: LicenseRef-Commercial
Requires-Python: >=3.10
Requires-Dist: cairosvg==2.7.1
Requires-Dist: Jinja2==3.1.4
Requires-Dist: latex==0.7.0
Requires-Dist: mistune==2.0.5
Requires-Dist: pyyaml==6.0.1
Requires-Dist: Pillow==12.0.0
Requires-Dist: cyclopts==3.24.0
Provides-Extra: dev
Requires-Dist: coverage; extra == "dev"
Requires-Dist: flake8; extra == "dev"
Requires-Dist: flake8-annotations; extra == "dev"
Requires-Dist: flake8-bandit; extra == "dev"
Requires-Dist: flake8-broken-line; extra == "dev"
Requires-Dist: flake8-bugbear; extra == "dev"
Requires-Dist: flake8-builtins; extra == "dev"
Requires-Dist: flake8-comprehensions; extra == "dev"
Requires-Dist: flake8-eradicate; extra == "dev"
Requires-Dist: flake8-executable; extra == "dev"
Requires-Dist: flake8-fixme; extra == "dev"
Requires-Dist: flake8-printf-formatting; extra == "dev"
Requires-Dist: flake8-return; extra == "dev"
Requires-Dist: flake8-walrus; extra == "dev"
Requires-Dist: pytest; extra == "dev"
Requires-Dist: ty==0.0.1a26; extra == "dev"
Requires-Dist: types-PyYAML; extra == "dev"
